{
      "MyAccount": {
            "Name": "MyAccount",
            "Index": "NIFTY",
            "Month": "6",
            "ExpiryDate": "22",
            "Strike": 0,
            "HedgeStrike": 200,
            "StopLoss": 35,
            "HedgeQty": 500,
            "Qty": 400,
            "Hour": 9,
            "Min": 44,
            "Seconds": 59,
            "Type": "NRML",
            "SLType": "TrailToCost",
            "Automatic": "True",
            "CEPrice": 0,
            "PEPrice": 0,
            "CESL": 0,
            "PESL": 0,
            "ATMStrike": 0
      },
      "MyAccount2": {
            "Name": "MyAccount2",
            "Index": "NIFTY",
            "Month": "6",
            "ExpiryDate": "22",
            "Strike": 0,
            "HedgeStrike": 200,
            "StopLoss": 35,
            "HedgeQty": 500,
            "Qty": 400,
            "Hour": 10,
            "Min": 29,
            "Seconds": 59,
            "Type": "NRML",
            "SLType": "TrailToCost",
            "Automatic": "True",
            "CEPrice": 0,
            "PEPrice": 0,
            "CESL": 0,
            "PESL": 0,
            "ATMStrike": 0
      },
      "Rahul2": {
            "Name": "Rahul2",
            "Index": "NIFTY",
            "Month": "6",
            "ExpiryDate": "22",
            "Strike": 0,
            "HedgeStrike": 200,
            "StopLoss": 35,
            "HedgeQty": 550,
            "Qty": 450,
            "Hour": 10,
            "Min": 29,
            "Seconds": 59,
            "Type": "NRML",
            "SLType": "TrailToCost",
            "Automatic": "True",
            "CEPrice": 0,
            "PEPrice": 0,
            "CESL": 0,
            "PESL": 0,
            "ATMStrike": 0
      },
      "Nirmal1": {
            "Name": "Nirmal1",
            "Index": "NIFTY",
            "Month": "6",
            "ExpiryDate": "22",
            "Strike": 0,
            "HedgeStrike": 200,
            "StopLoss": 35,
            "HedgeQty": 1050,
            "Qty": 800,
            "Hour": 9,
            "Min": 44,
            "Seconds": 59,
            "Type": "NRML",
            "SLType": "TrailToCost",
            "Automatic": "True",
            "CEPrice": 0,
            "PEPrice": 0,
            "CESL": 0,
            "PESL": 0,
            "ATMStrike": 0
      },
      "Nirmal2": {
            "Name": "Nirmal2",
            "Index": "NIFTY",
            "Month": "6",
            "ExpiryDate": "22",
            "Strike": 0,
            "HedgeStrike": 200,
            "StopLoss": 35,
            "HedgeQty": 1050,
            "Qty": 800,
            "Hour": 10,
            "Min": 29,
            "Seconds": 59,
            "Type": "NRML",
            "SLType": "TrailToCost",
            "Automatic": "True",
            "CEPrice": 0,
            "PEPrice": 0,
            "CESL": 0,
            "PESL": 0,
            "ATMStrike": 0
      },
      "Rahul1": {
            "Name": "Rahul1",
            "Index": "NIFTY",
            "Month": "6",
            "ExpiryDate": "22",
            "Strike": 0,
            "HedgeStrike": 200,
            "StopLoss": 35,
            "HedgeQty": 550,
            "Qty": 450,
            "Hour": 9,
            "Min": 44,
            "Seconds": 59,
            "Type": "NRML",
            "SLType": "TrailToCost",
            "Automatic": "True",
            "CEPrice": 0,
            "PEPrice": 0,
            "CESL": 0,
            "PESL": 0,
            "ATMStrike": 0
      },
      "Sumit2": {
            "Name": "Sumit2",
            "Index": "NIFTY",
            "Month": "6",
            "ExpiryDate": "22",
            "Strike": 0,
            "HedgeStrike": 200,
            "StopLoss": 35,
            "HedgeQty": 800,
            "Qty": 600,
            "Hour": 10,
            "Min": 29,
            "Seconds": 59,
            "Type": "NRML",
            "SLType": "TrailToCost",
            "Automatic": "True",
            "CEPrice": 0,
            "PEPrice": 0,
            "CESL": 0,
            "PESL": 0,
            "ATMStrike": 0
      },
      "Sumit1": {
            "Name": "Sumit1",
            "Index": "NIFTY",
            "Month": "6",
            "ExpiryDate": "22",
            "Strike": 0,
            "HedgeStrike": 200,
            "StopLoss": 35,
            "HedgeQty": 800,
            "Qty": 600,
            "Hour": 9,
            "Min": 44,
            "Seconds": 59,
            "Type": "NRML",
            "SLType": "TrailToCost",
            "Automatic": "True",
            "CEPrice": 0,
            "PEPrice": 0,
            "CESL": 0,
            "PESL": 0,
            "ATMStrike": 0
      },
      "Joshi2": {
            "Name": "Joshi2",
            "Index": "NIFTY",
            "Month": "6",
            "ExpiryDate": "22",
            "Strike": 0,
            "HedgeStrike": 200,
            "StopLoss": 35,
            "HedgeQty": 1250,
            "Qty": 950,
            "Hour": 10,
            "Min": 29,
            "Seconds": 59,
            "Type": "NRML",
            "SLType": "TrailToCost",
            "Automatic": "True",
            "CEPrice": 0,
            "PEPrice": 0,
            "CESL": 0,
            "PESL": 0,
            "ATMStrike": 0
      },
      "Joshi1": {
            "Name": "Joshi1",
            "Index": "NIFTY",
            "Month": "6",
            "ExpiryDate": "22",
            "Strike": 0,
            "HedgeStrike": 200,
            "StopLoss": 35,
            "HedgeQty": 1250,
            "Qty": 950,
            "Hour": 9,
            "Min": 44,
            "Seconds": 59,
            "Type": "NRML",
            "SLType": "TrailToCost",
            "Automatic": "True",
            "CEPrice": 0,
            "PEPrice": 0,
            "CESL": 0,
            "PESL": 0,
            "ATMStrike": 0
      },
      "Ankit1": {
            "Name": "Ankit1",
            "Index": "NIFTY",
            "Month": "6",
            "ExpiryDate": "22",
            "Strike": 0,
            "HedgeStrike": 200,
            "StopLoss": 35,
            "HedgeQty": 1700,
            "Qty": 1300,
            "Hour": 9,
            "Min": 44,
            "Seconds": 59,
            "Type": "NRML",
            "SLType": "TrailToCost",
            "Automatic": "True",
            "CEPrice": 0,
            "PEPrice": 0,
            "CESL": 0,
            "PESL": 0,
            "ATMStrike": 0
      },
      "Ankit2": {
            "Name": "Ankit2",
            "Index": "NIFTY",
            "Month": "6",
            "ExpiryDate": "22",
            "Strike": 0,
            "HedgeStrike": 200,
            "StopLoss": 35,
            "HedgeQty": 1700,
            "Qty": 1300,
            "Hour": 10,
            "Min": 29,
            "Seconds": 59,
            "Type": "NRML",
            "SLType": "TrailToCost",
            "Automatic": "True",
            "CEPrice": 0,
            "PEPrice": 0,
            "CESL": 0,
            "PESL": 0,
            "ATMStrike": 0
      },
      "Dilip2": {
            "Name": "Dilip2",
            "Index": "NIFTY",
            "Month": "6",
            "ExpiryDate": "22",
            "Strike": 0,
            "HedgeStrike": 200,
            "StopLoss": 35,
            "HedgeQty": 1650,
            "Qty": 1250,
            "Hour": 10,
            "Min": 29,
            "Seconds": 59,
            "Type": "NRML",
            "SLType": "TrailToCost",
            "Automatic": "True",
            "CEPrice": 0,
            "PEPrice": 0,
            "CESL": 0,
            "PESL": 0,
            "ATMStrike": 0
      },
      "Sanam2": {
            "Name": "Sanam2",
            "Index": "NIFTY",
            "Month": "6",
            "ExpiryDate": "22",
            "Strike": 0,
            "HedgeStrike": 200,
            "StopLoss": 35,
            "HedgeQty": 1500,
            "Qty": 1150,
            "Hour": 10,
            "Min": 29,
            "Seconds": 59,
            "Type": "NRML",
            "SLType": "TrailToCost",
            "Automatic": "True",
            "CEPrice": 0,
            "PEPrice": 0,
            "CESL": 0,
            "PESL": 0,
            "ATMStrike": 0
      },
      "Dilip1": {
            "Name": "Dilip1",
            "Index": "NIFTY",
            "Month": "6",
            "ExpiryDate": "22",
            "Strike": 0,
            "HedgeStrike": 200,
            "StopLoss": 35,
            "HedgeQty": 1650,
            "Qty": 1250,
            "Hour": 9,
            "Min": 44,
            "Seconds": 59,
            "Type": "NRML",
            "SLType": "TrailToCost",
            "Automatic": "True",
            "CEPrice": 0,
            "PEPrice": 0,
            "CESL": 0,
            "PESL": 0,
            "ATMStrike": 0
      },
      "Rishee2": {
            "Name": "Rishee2",
            "Index": "NIFTY",
            "Month": "6",
            "ExpiryDate": "22",
            "Strike": 0,
            "HedgeStrike": 200,
            "StopLoss": 35,
            "HedgeQty": 1650,
            "Qty": 1250,
            "Hour": 10,
            "Min": 29,
            "Seconds": 59,
            "Type": "NRML",
            "SLType": "TrailToCost",
            "Automatic": "True",
            "CEPrice": 0,
            "PEPrice": 0,
            "CESL": 0,
            "PESL": 0,
            "ATMStrike": 0
      },
      "Manjunath2": {
            "Name": "Manjunath2",
            "Index": "NIFTY",
            "Month": "6",
            "ExpiryDate": "22",
            "Strike": 0,
            "HedgeStrike": 200,
            "StopLoss": 35,
            "HedgeQty": 2100,
            "Qty": 1450,
            "Hour": 10,
            "Min": 29,
            "Seconds": 59,
            "Type": "NRML",
            "SLType": "TrailToCost",
            "Automatic": "True",
            "CEPrice": 0,
            "PEPrice": 0,
            "CESL": 0,
            "PESL": 0,
            "ATMStrike": 0
      },
      "Sanam1": {
            "Name": "Sanam1",
            "Index": "NIFTY",
            "Month": "6",
            "ExpiryDate": "22",
            "Strike": 0,
            "HedgeStrike": 200,
            "StopLoss": 35,
            "HedgeQty": 1500,
            "Qty": 1150,
            "Hour": 9,
            "Min": 44,
            "Seconds": 59,
            "Type": "NRML",
            "SLType": "TrailToCost",
            "Automatic": "True",
            "CEPrice": 0,
            "PEPrice": 0,
            "CESL": 0,
            "PESL": 0,
            "ATMStrike": 0
      },
      "Manjunath1": {
            "Name": "Manjunath1",
            "Index": "NIFTY",
            "Month": "6",
            "ExpiryDate": "22",
            "Strike": 0,
            "HedgeStrike": 200,
            "StopLoss": 35,
            "HedgeQty": 2100,
            "Qty": 1450,
            "Hour": 9,
            "Min": 44,
            "Seconds": 59,
            "Type": "NRML",
            "SLType": "TrailToCost",
            "Automatic": "True",
            "CEPrice": 0,
            "PEPrice": 0,
            "CESL": 0,
            "PESL": 0,
            "ATMStrike": 0
      },
      "Milan1": {
            "Name": "Milan1",
            "Index": "NIFTY",
            "Month": "6",
            "ExpiryDate": "22",
            "Strike": 0,
            "HedgeStrike": 200,
            "StopLoss": 35,
            "HedgeQty": 2100,
            "Qty": 1600,
            "Hour": 9,
            "Min": 44,
            "Seconds": 59,
            "Type": "NRML",
            "SLType": "TrailToCost",
            "Automatic": "True",
            "CEPrice": 0,
            "PEPrice": 0,
            "CESL": 0,
            "PESL": 0,
            "ATMStrike": 0
      },
      "Milan2": {
            "Name": "Milan2",
            "Index": "NIFTY",
            "Month": "6",
            "ExpiryDate": "22",
            "Strike": 0,
            "HedgeStrike": 200,
            "StopLoss": 35,
            "HedgeQty": 2100,
            "Qty": 1600,
            "Hour": 10,
            "Min": 29,
            "Seconds": 59,
            "Type": "NRML",
            "SLType": "TrailToCost",
            "Automatic": "True",
            "CEPrice": 0,
            "PEPrice": 0,
            "CESL": 0,
            "PESL": 0,
            "ATMStrike": 0
      },
      "Harsh2": {
            "Name": "Harsh2",
            "Index": "NIFTY",
            "Month": "6",
            "ExpiryDate": "22",
            "Strike": 0,
            "HedgeStrike": 200,
            "StopLoss": 35,
            "HedgeQty": 2350,
            "Qty": 1800,
            "Hour": 10,
            "Min": 29,
            "Seconds": 59,
            "Type": "NRML",
            "SLType": "TrailToCost",
            "Automatic": "True",
            "CEPrice": 0,
            "PEPrice": 0,
            "CESL": 0,
            "PESL": 0,
            "ATMStrike": 0
      },
      "Rishee1": {
            "Name": "Rishee1",
            "Index": "NIFTY",
            "Month": "6",
            "ExpiryDate": "22",
            "Strike": 0,
            "HedgeStrike": 200,
            "StopLoss": 35,
            "HedgeQty": 2000,
            "Qty": 1500,
            "Hour": 9,
            "Min": 44,
            "Seconds": 59,
            "Type": "NRML",
            "SLType": "TrailToCost",
            "Automatic": "True",
            "CEPrice": 0,
            "PEPrice": 0,
            "CESL": 0,
            "PESL": 0,
            "ATMStrike": 0
      },
      "Harsh1": {
            "Name": "Harsh1",
            "Index": "NIFTY",
            "Month": "6",
            "ExpiryDate": "22",
            "Strike": 0,
            "HedgeStrike": 200,
            "StopLoss": 35,
            "HedgeQty": 2350,
            "Qty": 1800,
            "Hour": 9,
            "Min": 44,
            "Seconds": 59,
            "Type": "NRML",
            "SLType": "TrailToCost",
            "Automatic": "True",
            "CEPrice": 0,
            "PEPrice": 0,
            "CESL": 0,
            "PESL": 0,
            "ATMStrike": 0
      },
      "Riyaaz3": {
            "Name": "Riyaaz3",
            "Index": "NIFTY",
            "Month": "6",
            "ExpiryDate": "22",
            "Strike": 0,
            "HedgeStrike": 200,
            "StopLoss": 35,
            "HedgeQty": 2250,
            "Qty": 1650,
            "Hour": 11,
            "Min": 29,
            "Seconds": 59,
            "Type": "NRML",
            "SLType": "TrailToCost",
            "Automatic": "True",
            "CEPrice": 0,
            "PEPrice": 0,
            "CESL": 0,
            "PESL": 0,
            "ATMStrike": 0
      },
      "Parag1": {
            "Name": "Parag1",
            "Index": "NIFTY",
            "Month": "6",
            "ExpiryDate": "22",
            "Strike": 0,
            "HedgeStrike": 200,
            "StopLoss": 35,
            "HedgeQty": 2250,
            "Qty": 1700,
            "Hour": 9,
            "Min": 44,
            "Seconds": 59,
            "Type": "NRML",
            "SLType": "TrailToCost",
            "Automatic": "True",
            "CEPrice": 0,
            "PEPrice": 0,
            "CESL": 0,
            "PESL": 0,
            "ATMStrike": 0
      },
      "Parag2": {
            "Name": "Parag2",
            "Index": "NIFTY",
            "Month": "6",
            "ExpiryDate": "22",
            "Strike": 0,
            "HedgeStrike": 200,
            "StopLoss": 35,
            "HedgeQty": 2250,
            "Qty": 1700,
            "Hour": 10,
            "Min": 29,
            "Seconds": 59,
            "Type": "NRML",
            "SLType": "TrailToCost",
            "Automatic": "True",
            "CEPrice": 0,
            "PEPrice": 0,
            "CESL": 0,
            "PESL": 0,
            "ATMStrike": 0
      },
      "Vijet2": {
            "Name": "Vijet2",
            "Index": "NIFTY",
            "Month": "6",
            "ExpiryDate": "22",
            "Strike": 0,
            "HedgeStrike": 200,
            "StopLoss": 35,
            "HedgeQty": 3250,
            "Qty": 2450,
            "Hour": 10,
            "Min": 29,
            "Seconds": 59,
            "Type": "NRML",
            "SLType": "TrailToCost",
            "Automatic": "True",
            "CEPrice": 0,
            "PEPrice": 0,
            "CESL": 0,
            "PESL": 0,
            "ATMStrike": 0
      },
      "Vijet1": {
            "Name": "Vijet1",
            "Index": "NIFTY",
            "Month": "6",
            "ExpiryDate": "22",
            "Strike": 0,
            "HedgeStrike": 200,
            "StopLoss": 35,
            "HedgeQty": 3250,
            "Qty": 2450,
            "Hour": 9,
            "Min": 44,
            "Seconds": 59,
            "Type": "NRML",
            "SLType": "TrailToCost",
            "Automatic": "True",
            "CEPrice": 0,
            "PEPrice": 0,
            "CESL": 0,
            "PESL": 0,
            "ATMStrike": 0
      },
      "Rajshekhar2": {
            "Name": "Rajshekhar2",
            "Index": "NIFTY",
            "Month": "6",
            "ExpiryDate": "22",
            "Strike": 0,
            "HedgeStrike": 200,
            "StopLoss": 35,
            "HedgeQty": 3650,
            "Qty": 2550,
            "Hour": 10,
            "Min": 29,
            "Seconds": 59,
            "Type": "NRML",
            "SLType": "TrailToCost",
            "Automatic": "True",
            "CEPrice": 0,
            "PEPrice": 0,
            "CESL": 0,
            "PESL": 0,
            "ATMStrike": 0
      },
      "Rajshekhar1": {
            "Name": "Rajshekhar1",
            "Index": "NIFTY",
            "Month": "6",
            "ExpiryDate": "22",
            "Strike": 0,
            "HedgeStrike": 200,
            "StopLoss": 35,
            "HedgeQty": 3650,
            "Qty": 2550,
            "Hour": 9,
            "Min": 44,
            "Seconds": 59,
            "Type": "NRML",
            "SLType": "TrailToCost",
            "Automatic": "True",
            "CEPrice": 0,
            "PEPrice": 0,
            "CESL": 0,
            "PESL": 0,
            "ATMStrike": 0
      },
      "Riyaaz2": {
            "Name": "Riyaaz2",
            "Index": "NIFTY",
            "Month": "6",
            "ExpiryDate": "22",
            "Strike": 0,
            "HedgeStrike": 200,
            "StopLoss": 35,
            "HedgeQty": 4550,
            "Qty": 3450,
            "Hour": 10,
            "Min": 29,
            "Seconds": 59,
            "Type": "NRML",
            "SLType": "TrailToCost",
            "Automatic": "True",
            "CEPrice": 0,
            "PEPrice": 0,
            "CESL": 0,
            "PESL": 0,
            "ATMStrike": 0
      },
      "Riyaaz1": {
            "Name": "Riyaaz1",
            "Index": "NIFTY",
            "Month": "6",
            "ExpiryDate": "22",
            "Strike": 0,
            "HedgeStrike": 200,
            "StopLoss": 35,
            "HedgeQty": 4850,
            "Qty": 3700,
            "Hour": 9,
            "Min": 44,
            "Seconds": 59,
            "Type": "NRML",
            "SLType": "TrailToCost",
            "Automatic": "True",
            "CEPrice": 0,
            "PEPrice": 0,
            "CESL": 0,
            "PESL": 0,
            "ATMStrike": 0
      }
}