{
      "MyAccount": {
            "Name": "MyAccount",
            "Index": "NIFTY",
            "Month": "6",
            "ExpiryDate": "08",
            "Strike": 0,
            "HedgeStrike": 350,
            "StopLoss": 35,
            "HedgeQty": 300,
            "Qty": 250,
            "Hour": 9,
            "Min": 44,
            "Seconds": 59,
            "Type": "MIS",
            "SLType": "TrailToCost"
      },
      "MyAccount2": {
            "Name": "MyAccount2",
            "Index": "NIFTY",
            "Month": "6",
            "ExpiryDate": "08",
            "Strike": 0,
            "HedgeStrike": 350,
            "StopLoss": 35,
            "HedgeQty": 300,
            "Qty": 250,
            "Hour": 10,
            "Min": 29,
            "Seconds": 59,
            "Type": "MIS",
            "SLType": "TrailToCost"
      },
      "Sumit2": {
            "Name": "Sumit2",
            "Index": "NIFTY",
            "Month": "6",
            "ExpiryDate": "08",
            "Strike": 0,
            "HedgeStrike": 350,
            "StopLoss": 35,
            "HedgeQty": 650,
            "Qty": 450,
            "Hour": 10,
            "Min": 29,
            "Seconds": 59,
            "Type": "MIS",
            "SLType": "TrailToCost"
      },
      "Nirmal2": {
            "Name": "Nirmal2",
            "Index": "NIFTY",
            "Month": "6",
            "ExpiryDate": "08",
            "Strike": 0,
            "HedgeStrike": 350,
            "StopLoss": 35,
            "HedgeQty": 700,
            "Qty": 500,
            "Hour": 10,
            "Min": 29,
            "Seconds": 59,
            "Type": "MIS",
            "SLType": "TrailToCost"
      },
      "Nirmal1": {
            "Name": "Nirmal1",
            "Index": "NIFTY",
            "Month": "6",
            "ExpiryDate": "08",
            "Strike": 0,
            "HedgeStrike": 350,
            "StopLoss": 35,
            "HedgeQty": 700,
            "Qty": 500,
            "Hour": 9,
            "Min": 44,
            "Seconds": 59,
            "Type": "MIS",
            "SLType": "TrailToCost"
      },
      "Sumit1": {
            "Name": "Sumit1",
            "Index": "NIFTY",
            "Month": "6",
            "ExpiryDate": "08",
            "Strike": 0,
            "HedgeStrike": 350,
            "StopLoss": 35,
            "HedgeQty": 650,
            "Qty": 450,
            "Hour": 9,
            "Min": 44,
            "Seconds": 59,
            "Type": "MIS",
            "SLType": "TrailToCost"
      },
      "Dilip1": {
            "Name": "Dilip1",
            "Index": "NIFTY",
            "Month": "6",
            "ExpiryDate": "08",
            "Strike": 0,
            "HedgeStrike": 350,
            "StopLoss": 35,
            "HedgeQty": 1250,
            "Qty": 900,
            "Hour": 9,
            "Min": 44,
            "Seconds": 59,
            "Type": "MIS",
            "SLType": "TrailToCost"
      },
      "Dilip2": {
            "Name": "Dilip2",
            "Index": "NIFTY",
            "Month": "6",
            "ExpiryDate": "08",
            "Strike": 0,
            "HedgeStrike": 350,
            "StopLoss": 35,
            "HedgeQty": 1250,
            "Qty": 900,
            "Hour": 10,
            "Min": 29,
            "Seconds": 59,
            "Type": "MIS",
            "SLType": "TrailToCost"
      },
      "Sanam2": {
            "Name": "Sanam2",
            "Index": "NIFTY",
            "Month": "6",
            "ExpiryDate": "08",
            "Strike": 0,
            "HedgeStrike": 350,
            "StopLoss": 35,
            "HedgeQty": 950,
            "Qty": 700,
            "Hour": 10,
            "Min": 29,
            "Seconds": 59,
            "Type": "MIS",
            "SLType": "TrailToCost"
      },
      "Sanam1": {
            "Name": "Sanam1",
            "Index": "NIFTY",
            "Month": "6",
            "ExpiryDate": "08",
            "Strike": 0,
            "HedgeStrike": 350,
            "StopLoss": 35,
            "HedgeQty": 950,
            "Qty": 700,
            "Hour": 9,
            "Min": 44,
            "Seconds": 59,
            "Type": "MIS",
            "SLType": "TrailToCost"
      },
      "Ankit2": {
            "Name": "Ankit2",
            "Index": "NIFTY",
            "Month": "6",
            "ExpiryDate": "08",
            "Strike": 0,
            "HedgeStrike": 350,
            "StopLoss": 35,
            "HedgeQty": 1250,
            "Qty": 900,
            "Hour": 10,
            "Min": 29,
            "Seconds": 59,
            "Type": "MIS",
            "SLType": "TrailToCost"
      },
      "Rishee2": {
            "Name": "Rishee2",
            "Index": "NIFTY",
            "Month": "6",
            "ExpiryDate": "08",
            "Strike": 0,
            "HedgeStrike": 350,
            "StopLoss": 35,
            "HedgeQty": 1300,
            "Qty": 900,
            "Hour": 10,
            "Min": 29,
            "Seconds": 59,
            "Type": "MIS",
            "SLType": "TrailToCost"
      },
      "Ankit1": {
            "Name": "Ankit1",
            "Index": "NIFTY",
            "Month": "6",
            "ExpiryDate": "08",
            "Strike": 0,
            "HedgeStrike": 350,
            "StopLoss": 35,
            "HedgeQty": 1250,
            "Qty": 900,
            "Hour": 9,
            "Min": 44,
            "Seconds": 59,
            "Type": "MIS",
            "SLType": "TrailToCost"
      },
      "Parag2": {
            "Name": "Parag2",
            "Index": "NIFTY",
            "Month": "6",
            "ExpiryDate": "08",
            "Strike": 0,
            "HedgeStrike": 350,
            "StopLoss": 35,
            "HedgeQty": 1850,
            "Qty": 1300,
            "Hour": 10,
            "Min": 29,
            "Seconds": 59,
            "Type": "MIS",
            "SLType": "TrailToCost"
      },
      "Manjunath1": {
            "Name": "Manjunath1",
            "Index": "NIFTY",
            "Month": "6",
            "ExpiryDate": "08",
            "Strike": 0,
            "HedgeStrike": 350,
            "StopLoss": 35,
            "HedgeQty": 1400,
            "Qty": 1000,
            "Hour": 9,
            "Min": 44,
            "Seconds": 59,
            "Type": "MIS",
            "SLType": "TrailToCost"
      },
      "Parag1": {
            "Name": "Parag1",
            "Index": "NIFTY",
            "Month": "6",
            "ExpiryDate": "08",
            "Strike": 0,
            "HedgeStrike": 350,
            "StopLoss": 35,
            "HedgeQty": 1850,
            "Qty": 1300,
            "Hour": 9,
            "Min": 44,
            "Seconds": 59,
            "Type": "MIS",
            "SLType": "TrailToCost"
      },
      "Manjunath2": {
            "Name": "Manjunath2",
            "Index": "NIFTY",
            "Month": "6",
            "ExpiryDate": "08",
            "Strike": 0,
            "HedgeStrike": 350,
            "StopLoss": 35,
            "HedgeQty": 1400,
            "Qty": 1000,
            "Hour": 10,
            "Min": 29,
            "Seconds": 59,
            "Type": "MIS",
            "SLType": "TrailToCost"
      },
      "Riyaaz3": {
            "Name": "Riyaaz3",
            "Index": "NIFTY",
            "Month": "6",
            "ExpiryDate": "08",
            "Strike": 0,
            "HedgeStrike": 350,
            "StopLoss": 35,
            "HedgeQty": 1650,
            "Qty": 1200,
            "Hour": 11,
            "Min": 29,
            "Seconds": 59,
            "Type": "MIS",
            "SLType": "TrailToCost"
      },
      "Rishee1": {
            "Name": "Rishee1",
            "Index": "NIFTY",
            "Month": "6",
            "ExpiryDate": "08",
            "Strike": 0,
            "HedgeStrike": 350,
            "StopLoss": 35,
            "HedgeQty": 1550,
            "Qty": 1100,
            "Hour": 9,
            "Min": 44,
            "Seconds": 59,
            "Type": "MIS",
            "SLType": "TrailToCost"
      },
      "Vijet2": {
            "Name": "Vijet2",
            "Index": "NIFTY",
            "Month": "6",
            "ExpiryDate": "08",
            "Strike": 0,
            "HedgeStrike": 350,
            "StopLoss": 35,
            "HedgeQty": 2600,
            "Qty": 1800,
            "Hour": 10,
            "Min": 29,
            "Seconds": 59,
            "Type": "MIS",
            "SLType": "TrailToCost"
      },
      "Milan2": {
            "Name": "Milan2",
            "Index": "NIFTY",
            "Month": "6",
            "ExpiryDate": "08",
            "Strike": 0,
            "HedgeStrike": 350,
            "StopLoss": 35,
            "HedgeQty": 1650,
            "Qty": 1150,
            "Hour": 10,
            "Min": 29,
            "Seconds": 59,
            "Type": "MIS",
            "SLType": "TrailToCost"
      },
      "Vijet1": {
            "Name": "Vijet1",
            "Index": "NIFTY",
            "Month": "6",
            "ExpiryDate": "08",
            "Strike": 0,
            "HedgeStrike": 350,
            "StopLoss": 35,
            "HedgeQty": 2600,
            "Qty": 1800,
            "Hour": 9,
            "Min": 44,
            "Seconds": 59,
            "Type": "MIS",
            "SLType": "TrailToCost"
      },
      "Milan1": {
            "Name": "Milan1",
            "Index": "NIFTY",
            "Month": "6",
            "ExpiryDate": "08",
            "Strike": 0,
            "HedgeStrike": 350,
            "StopLoss": 35,
            "HedgeQty": 1650,
            "Qty": 1150,
            "Hour": 9,
            "Min": 44,
            "Seconds": 59,
            "Type": "MIS",
            "SLType": "TrailToCost"
      },
      "Rajshekhar1": {
            "Name": "Rajshekhar1",
            "Index": "NIFTY",
            "Month": "6",
            "ExpiryDate": "08",
            "Strike": 0,
            "HedgeStrike": 350,
            "StopLoss": 35,
            "HedgeQty": 2750,
            "Qty": 1900,
            "Hour": 9,
            "Min": 44,
            "Seconds": 59,
            "Type": "MIS",
            "SLType": "TrailToCost"
      },
      "Rajshekhar2": {
            "Name": "Rajshekhar2",
            "Index": "NIFTY",
            "Month": "6",
            "ExpiryDate": "08",
            "Strike": 0,
            "HedgeStrike": 350,
            "StopLoss": 35,
            "HedgeQty": 2750,
            "Qty": 1900,
            "Hour": 10,
            "Min": 29,
            "Seconds": 59,
            "Type": "MIS",
            "SLType": "TrailToCost"
      },
      "Riyaaz1": {
            "Name": "Riyaaz1",
            "Index": "NIFTY",
            "Month": "6",
            "ExpiryDate": "08",
            "Strike": 0,
            "HedgeStrike": 350,
            "StopLoss": 35,
            "HedgeQty": 3800,
            "Qty": 2700,
            "Hour": 9,
            "Min": 44,
            "Seconds": 59,
            "Type": "MIS",
            "SLType": "TrailToCost"
      },
      "Harsh1": {
            "Name": "Harsh1",
            "Index": "NIFTY",
            "Month": "6",
            "ExpiryDate": "08",
            "Strike": 0,
            "HedgeStrike": 350,
            "StopLoss": 35,
            "HedgeQty": 1750,
            "Qty": 1250,
            "Hour": 9,
            "Min": 44,
            "Seconds": 59,
            "Type": "MIS",
            "SLType": "TrailToCost"
      },
      "Harsh2": {
            "Name": "Harsh2",
            "Index": "NIFTY",
            "Month": "6",
            "ExpiryDate": "08",
            "Strike": 0,
            "HedgeStrike": 350,
            "StopLoss": 35,
            "HedgeQty": 1750,
            "Qty": 1250,
            "Hour": 10,
            "Min": 29,
            "Seconds": 59,
            "Type": "MIS",
            "SLType": "TrailToCost"
      },
      "Riyaaz2": {
            "Name": "Riyaaz2",
            "Index": "NIFTY",
            "Month": "6",
            "ExpiryDate": "08",
            "Strike": 0,
            "HedgeStrike": 350,
            "StopLoss": 35,
            "HedgeQty": 3400,
            "Qty": 2350,
            "Hour": 10,
            "Min": 29,
            "Seconds": 59,
            "Type": "MIS",
            "SLType": "TrailToCost"
      }
}